no_log_tears/__init__.py
no_log_tears/config.py
no_log_tears/formatter/__init__.py
no_log_tears/formatter/datetime.py
no_log_tears/formatter/json.py
no_log_tears/formatter/soft.py
no_log_tears/formatter/traceback.py
no_log_tears/logger.py
no_log_tears/mixin.py
no_log_tears/py.typed
no_log_tears/record.py
no_log_tears/settings.py
no_log_tears-0.2.1.dist-info/LICENSE
no_log_tears-0.2.1.dist-info/METADATA
no_log_tears-0.2.1.dist-info/WHEEL
no_log_tears-0.2.1.dist-info/RECORD
