Metadata-Version: 2.3
Name: no-log-tears
Version: 0.2.1
Summary: NoLogTears is a simple extension of Python's built-in logging library, designed to make logging easier, more efficient, and headache-free—no more tears over log management.
License: MIT
Keywords: python,logging
Author: zerlok
Author-email: danil.troshnev@gmail.com
Requires-Python: >=3.9,<4.0
Classifier: Development Status :: 3 - Alpha
Classifier: Intended Audience :: Developers
Classifier: License :: OSI Approved :: MIT License
Classifier: Operating System :: OS Independent
Classifier: Programming Language :: Python :: 3
Classifier: Programming Language :: Python :: 3.9
Classifier: Programming Language :: Python :: 3.10
Classifier: Programming Language :: Python :: 3.11
Classifier: Programming Language :: Python :: 3.12
Classifier: Programming Language :: Python :: 3.13
Classifier: Topic :: System :: Logging
Classifier: Typing :: Typed
Provides-Extra: all
Requires-Dist: pydantic (>=2.10.6,<3.0.0) ; extra == "all"
Requires-Dist: pydantic-settings[yaml] (>=2.7.1,<3.0.0) ; extra == "all"
Project-URL: Homepage, https://github.com/zerlok/no-log-tears
Project-URL: Issues, https://github.com/zerlok/no-log-tears/issues
